MANIFEST.in
README
__init__.py
__pkginfo__.py
schema.py
setup.py
uiprops.py
views.py
cubicweb_basket.egg-info/PKG-INFO
cubicweb_basket.egg-info/SOURCES.txt
cubicweb_basket.egg-info/dependency_links.txt
cubicweb_basket.egg-info/requires.txt
cubicweb_basket.egg-info/top_level.txt
data/icon_basket.gif
i18n/en.po
i18n/fr.po
migration/postcreate.py