Metadata-Version: 1.0
Name: cubicweb-basket
Version: 1.4.0
Summary: shopping cart component for the CubicWeb framework
Home-page: http://www.cubicweb.org/project/cubicweb-basket
Author: Logilab
Author-email: contact@logilab.fr
License: LGPL
Platform: UNKNOWN
